{
	"sn": "facebook",
	"lastEventDate": "28.12.2022 18:59 script_3_a_8",
	"status": 2,
	"id": "100088531538480",
	"name": "",
	"amountFriends": "",
	"screenname": "Rafaela Goncalvez",
	"birthdate": "1999 February 2",
	"country": "Brazil",
	"isAvatarExists": false,
	"cookie": [
		{
			"domain": ".facebook.com",
			"expirationDate": 1705337897.64983,
			"hostOnly": false,
			"httpOnly": true,
			"name": "sb",
			"path": "/",
			"sameSite": "no_restriction",
			"secure": true,
			"session": false,
			"storeId": "0",
			"value": "HgyWY-Jz8bwGQJTnV4ghf2Xx"
		},
		{
			"domain": ".facebook.com",
			"expirationDate": 1705337881.018899,
			"hostOnly": false,
			"httpOnly": true,
			"name": "datr",
			"path": "/",
			"sameSite": "no_restriction",
			"secure": true,
			"session": false,
			"storeId": "0",
			"value": "HgyWY6W5_Sc_esOr4oPs1z5e"
		},
		{
			"domain": ".facebook.com",
			"expirationDate": 1672770356,
			"hostOnly": false,
			"httpOnly": false,
			"name": "dpr",
			"path": "/",
			"sameSite": "no_restriction",
			"secure": true,
			"session": false,
			"storeId": "0",
			"value": "1.25"
		},
		{
			"domain": ".facebook.com",
			"expirationDate": 1703701445.750525,
			"hostOnly": false,
			"httpOnly": false,
			"name": "c_user",
			"path": "/",
			"sameSite": "no_restriction",
			"secure": true,
			"session": false,
			"storeId": "0",
			"value": "100088531538480"
		},
		{
			"domain": ".facebook.com",
			"expirationDate": 1672770349,
			"hostOnly": false,
			"httpOnly": false,
			"name": "wd",
			"path": "/",
			"sameSite": "lax",
			"secure": true,
			"session": false,
			"storeId": "0",
			"value": "1536x668"
		},
		{
			"domain": ".facebook.com",
			"expirationDate": 1703701445.750578,
			"hostOnly": false,
			"httpOnly": true,
			"name": "xs",
			"path": "/",
			"sameSite": "no_restriction",
			"secure": true,
			"session": false,
			"storeId": "0",
			"value": "23%3A3jJdMLvb0N-rMA%3A2%3A1670777902%3A-1%3A2541%3A%3AAcVNC43T4m-HAQ_4RZWPhohXdzd4Xn2ICO7t9SWr1l8"
		},
		{
			"domain": ".facebook.com",
			"expirationDate": 1679941444.750595,
			"hostOnly": false,
			"httpOnly": true,
			"name": "fr",
			"path": "/",
			"sameSite": "no_restriction",
			"secure": true,
			"session": false,
			"storeId": "0",
			"value": "0ouqpic9maVJ6zZwv.AWVZr3GDBYeZk5YGidPehsg0I0U.BjqzhG.j8.AAA.0.0.BjqzhG.AWU3Ktfvp_0"
		},
		{
			"domain": ".facebook.com",
			"hostOnly": false,
			"httpOnly": false,
			"name": "presence",
			"path": "/",
			"sameSite": "unspecified",
			"secure": true,
			"session": true,
			"storeId": "0",
			"value": "C%7B%22lm3%22%3A%22u.100080491506192%22%2C%22t3%22%3A%5B%5D%2C%22utc3%22%3A1672165556454%2C%22v%22%3A1%7D"
		}
	]
}