{
	"sn": "facebook",
	"lastEventDate": "11.12.2022 15:02 Costa_Dia_1",
	"status": 2,
	"id": "100088432122503",
	"name": "",
	"amountFriends": "",
	"screenname": "Brenda Alvez",
	"birthdate": "2000 May 5",
	"country": "Brazil",
	"isAvatarExists": false,
	"cookie": [
		{
			"domain": ".facebook.com",
			"expirationDate": 1704903006.765172,
			"hostOnly": false,
			"httpOnly": true,
			"name": "datr",
			"path": "/",
			"sameSite": "no_restriction",
			"secure": true,
			"session": false,
			"storeId": "0",
			"value": "XmmPY7M8hKB01rBCPomrl4BG"
		},
		{
			"domain": ".facebook.com",
			"expirationDate": 1705330341.525302,
			"hostOnly": false,
			"httpOnly": true,
			"name": "sb",
			"path": "/",
			"sameSite": "no_restriction",
			"secure": true,
			"session": false,
			"storeId": "0",
			"value": "XmmPYyFf-9krwvOCBO9W5d5h"
		},
		{
			"domain": ".facebook.com",
			"hostOnly": false,
			"httpOnly": false,
			"name": "m_pixel_ratio",
			"path": "/",
			"sameSite": "unspecified",
			"secure": true,
			"session": true,
			"storeId": "0",
			"value": "1.25"
		},
		{
			"domain": ".facebook.com",
			"expirationDate": 1671375767,
			"hostOnly": false,
			"httpOnly": false,
			"name": "dpr",
			"path": "/",
			"sameSite": "no_restriction",
			"secure": true,
			"session": false,
			"storeId": "0",
			"value": "1.25"
		},
		{
			"domain": ".facebook.com",
			"expirationDate": 1702306338.525389,
			"hostOnly": false,
			"httpOnly": false,
			"name": "c_user",
			"path": "/",
			"sameSite": "no_restriction",
			"secure": true,
			"session": false,
			"storeId": "0",
			"value": "100088432122503"
		},
		{
			"domain": ".facebook.com",
			"expirationDate": 1702306338.525404,
			"hostOnly": false,
			"httpOnly": true,
			"name": "xs",
			"path": "/",
			"sameSite": "no_restriction",
			"secure": true,
			"session": false,
			"storeId": "0",
			"value": "2%3AgjISRCI6tbpuPA%3A2%3A1670770345%3A-1%3A-1"
		},
		{
			"domain": ".facebook.com",
			"expirationDate": 1671375752,
			"hostOnly": false,
			"httpOnly": false,
			"name": "wd",
			"path": "/",
			"sameSite": "lax",
			"secure": true,
			"session": false,
			"storeId": "0",
			"value": "1536x668"
		},
		{
			"domain": ".facebook.com",
			"expirationDate": 1678546845.989642,
			"hostOnly": false,
			"httpOnly": true,
			"name": "fr",
			"path": "/",
			"sameSite": "no_restriction",
			"secure": true,
			"session": false,
			"storeId": "0",
			"value": "0kUePEDpbDYPWknUj.AWWo6lKdFxkl0qhDlkItIFRDQgc.Bjj2le.bD.AAA.0.0.BjlfCl.AWUX1FplbVs"
		},
		{
			"domain": ".facebook.com",
			"hostOnly": false,
			"httpOnly": false,
			"name": "presence",
			"path": "/",
			"sameSite": "unspecified",
			"secure": true,
			"session": true,
			"storeId": "0",
			"value": "C%7B%22t3%22%3A%5B%5D%2C%22utc3%22%3A1670770955495%2C%22v%22%3A1%7D"
		}
	]
}